SOMptimised/README.md
SOMptimised/__init__.py
SOMptimised/learning_rate.py
SOMptimised/metric.py
SOMptimised/neighbourhood.py
SOMptimised/som.py
SOMptimised/examples/iris_dataset/iris_dataset.csv
SOMptimised/examples/iris_dataset/predict_sepal_width.py
SOMptimised/examples/iris_dataset/som_iris.py
SOMptimised-1.1.0.dist-info/LICENSE
SOMptimised-1.1.0.dist-info/METADATA
SOMptimised-1.1.0.dist-info/WHEEL
SOMptimised-1.1.0.dist-info/top_level.txt
SOMptimised-1.1.0.dist-info/RECORD
