Metadata-Version: 2.1
Name: SOMptimised
Version: 1.1.0
Summary: An optimised Self Organising Map which can write and read its values into and from an external file.
Home-page: https://github.com/WilfriedMercier/SOMptimised
Author: Wilfried Mercier
Author-email: wilfried.mercier@irap.omp.eu
License: UNKNOWN
Project-URL: Bug Tracker, https://github.com/WilfriedMercier/SOMptimised/issues
Project-URL: Documentation, https://wilfriedmercier.github.io/SOMptimised/index.html
Platform: UNKNOWN
Classifier: Programming Language :: Python :: 3
Classifier: License :: OSI Approved :: MIT License
Classifier: Operating System :: OS Independent
Requires-Python: >=3.7
License-File: LICENSE
Requires-Dist: numpy (>=1.21)
Requires-Dist: colorama (>=0.4)
Requires-Dist: joblib (>=1.1)
